asgi_claim_validator/__init__.py
asgi_claim_validator/constants.py
asgi_claim_validator/decorators.py
asgi_claim_validator/exceptions.py
asgi_claim_validator/middleware.py
asgi_claim_validator/types.py
asgi_claim_validator-1.0.4.dist-info/LICENSE
asgi_claim_validator-1.0.4.dist-info/METADATA
asgi_claim_validator-1.0.4.dist-info/WHEEL
asgi_claim_validator-1.0.4.dist-info/RECORD
