Metadata-Version: 2.3
Name: asgi-claim-validator
Version: 1.0.4
Summary: A focused ASGI middleware for validating additional claims within JWT tokens to enhance token-based workflows.
License: GNU GPLv3
Keywords: asgi,async,claims,connexion,fastapi,jwt,middleware,request-duration,starlette,validator
Author: Fabio Greco
Author-email: fabio.greco.github@gmail.com
Maintainer: Fabio Greco
Maintainer-email: fabio.greco.github@gmail.com
Requires-Python: >=3.11,<4.0
Classifier: Development Status :: 5 - Production/Stable
Classifier: Environment :: Web Environment
Classifier: Framework :: FastAPI
Classifier: Intended Audience :: Developers
Classifier: License :: OSI Approved :: GNU General Public License v3 (GPLv3)
Classifier: License :: Other/Proprietary License
Classifier: Natural Language :: English
Classifier: Operating System :: OS Independent
Classifier: Programming Language :: Python
Classifier: Programming Language :: Python :: 3
Classifier: Programming Language :: Python :: 3.11
Classifier: Programming Language :: Python :: 3.12
Classifier: Programming Language :: Python :: 3.13
Classifier: Topic :: Internet
Classifier: Topic :: Internet :: WWW/HTTP
Classifier: Topic :: Software Development
Classifier: Topic :: Software Development :: Libraries
Classifier: Topic :: Software Development :: Libraries :: Application Frameworks
Classifier: Topic :: Software Development :: Libraries :: Python Modules
Classifier: Topic :: Utilities
Classifier: Typing :: Typed
Requires-Dist: joserfc (>=1.2.2)
Requires-Dist: jsonschema (>=4.23.0)
Requires-Dist: starlette (>=0.45.2)
Project-URL: Homepage, https://github.com/feteu/asgi-claim-validator
Project-URL: Repository, https://github.com/feteu/asgi-claim-validator
